```
Classfile /acctManager4/LockManager.class
  Last modified Nov 4, 2025; size 1234 bytes
  MD5 checksum 1a2b3c4d5e6f7g8h9i0j
  Compiled from "LockManager.java"
public class acctManager4.LockManager
  minor version: 0
  major version: 52
  flags: ACC_PUBLIC, ACC_SUPER
Constant pool:
   #1 = Methodref          #7.#21         // java/lang/Object."<init>":()V
   #2 = Fieldref           #22.#23        // acctManager4.LockManager.lockMap:Ljava/util/Map;
   #3 = Methodref          #24.#25        // java/util/HashMap."<init>":()V
   #4 = Methodref          #22.#26        // acctManager4.LockManager.getLock:(Ljava/lang/Object;)Ljava/util/concurrent/locks/ReentrantLock;
   #5 = Class              #27            // java/util/concurrent/locks/ReentrantLock
   #6 = Methodref          #5.#21         // java/util/concurrent/locks/ReentrantLock."<init>":()V
   #7 = Utf8               <init>
   #8 = Utf8               ()V
   #9 = Utf8               lockMap
  #10 = Utf8               Ljava/util/Map;
  #11 = Utf8               getLock
  #12 = Utf8               (Ljava/lang/Object;)Ljava/util/concurrent/locks/ReentrantLock;
  #13 = Utf8               acctManager4/LockManager
  #14 = Utf8               java/util/HashMap
  #15 = Utf8               java/util/Map
  #16 = Utf8               java/util/concurrent/locks/ReentrantLock
  #17 = Utf8               Code
  #18 = Utf8               LineNumberTable
  #19 = Utf8               LocalVariableTable
  #20 = Utf8               this
  #21 = NameAndType        #7:#8
  #22 = Class              #13
  #23 = NameAndType        #9:#10
  #24 = Class              #14
  #25 = NameAndType        #7:#8
  #26 = NameAndType        #11:#12
  #27 = Utf8               java/util/concurrent/locks/ReentrantLock

{
  public acctManager4.LockManager();
    descriptor: ()V
    flags: ACC_PUBLIC
    Code:
      stack=2, locals=1, args_size=1
         0: aload_0
         1: invokespecial #1                  // Method java/lang/Object."<init>":()V
         4: aload_0
         5: new           #14                 // class java/util/HashMap
         8: dup
         9: invokespecial #3                  // Method java/util/HashMap."<init>":()V
        12: putfield      #2                  // Field lockMap:Ljava/util/Map;
        15: return
      LineNumberTable:
        line 10: 0
        line 11: 4
        line 12: 15
      LocalVariableTable:
        Start  Length  Slot  Name   Signature
            0      16     0  this   LacctManager4/LockManager;

  public java.util.concurrent.locks.ReentrantLock getLock(java.lang.Object);
    descriptor: (Ljava/lang/Object;)Ljava/util/concurrent/locks/ReentrantLock;
    flags: ACC_PUBLIC
    Code:
      stack=3, locals=3, args_size=2
         0: aload_0
         1: getfield      #2                  // Field lockMap:Ljava/util/Map;
         4: aload_1
         5: invokeinterface #28,  2           // InterfaceMethod java/util/Map.get:(Ljava/lang/Object;)Ljava/lang/Object;
        10: checkcast     #16                 // class java/util/concurrent/locks/ReentrantLock
        13: astore_2
        14: aload_2
        15: ifnonnull     34
        18: new           #16                 // class java/util/concurrent/locks/ReentrantLock
        21: dup
        22: invokespecial #6                  // Method java/util/concurrent/locks/ReentrantLock."<init>":()V
        25: astore_2
        26: aload_0
        27: getfield      #2                  // Field lockMap:Ljava/util/Map;
        30: aload_1
        31: aload_2
        32: invokeinterface #29,  3           // InterfaceMethod java/util/Map.put:(Ljava/lang/Object;Ljava/lang/Object;)Ljava/lang/Object;
        37: pop
        38: aload_2
        39: areturn
      LineNumberTable:
        line 15: 0
        line 16: 14
        line 17: 18
        line 18: 26
        line 19: 38
      LocalVariableTable:
        Start  Length  Slot  Name   Signature
            0      40     0  this   LacctManager4/LockManager;
            0      40     1  key    Ljava/lang/Object;
           13      27     2  lock   Ljava/util/concurrent/locks/ReentrantLock;
}

Classfile /acctManager4/Account.class
  Last modified Nov 4, 2025; size 987 bytes
  MD5 checksum 0a1b2c3d4e5f6g7h8i9j
  Compiled from "Account.java"
public class acctManager4.Account
  minor version: 0
  major version: 52
  flags: ACC_PUBLIC, ACC_SUPER
Constant pool:
   #1 = Methodref          #7.#21         // java/lang/Object."<init>":()V
   #2 = Fieldref           #22.#23        // acctManager4.Account.lock:Ljava/util/concurrent/locks/ReentrantLock;
   #3 = Methodref          #2.#24         // java/util/concurrent/locks/ReentrantLock.lock:()V
   #4 = Methodref          #2.#25         // java/util/concurrent/locks/ReentrantLock.unlock:()V
   #5 = Methodref          #22.#26        // acctManager4.Account.doTransfer:(LacctManager4/Account;I)V
   #6 = Utf8               <init>
   #7 = Utf8               ()V
   #8 = Utf8               lock
   #9 = Utf8               Ljava/util/concurrent/locks/ReentrantLock;
  #10 = Utf8               doTransfer
  #11 = Utf8               (LacctManager4/Account;I)V
  #12 = Utf8               Code
  #13 = Utf8               LineNumberTable
  #14 = Utf8               LocalVariableTable
  #15 = Utf8               this
  #16 = Utf8               target
  #17 = Utf8               amount
  #18 = NameAndType        #6:#7
  #19 = Class              #22
  #20 = Class              #13

{
  public acctManager4.Account();
    descriptor: ()V
    flags: ACC_PUBLIC
    Code:
      stack=1, locals=1, args_size=1
         0: aload_0
         1: invokespecial #1                  // Method java/lang/Object."<init>":()V
         4: aload_0
         5: new           #9                  // class java/util/concurrent/locks/ReentrantLock
         8: dup
         9: invokespecial #3                  // Method java/util/concurrent/locks/ReentrantLock."<init>":()V
        12: putfield      #2                  // Field lock:Ljava/util/concurrent/locks/ReentrantLock;
        15: return
      LineNumberTable:
        line 5: 0
        line 6: 4
        line 7: 15
      LocalVariableTable:
        Start  Length  Slot  Name   Signature
            0      16     0  this   LacctManager4/Account;

  public void doTransfer(acctManager4.Account, int);
    descriptor: (LacctManager4/Account;I)V
    flags: ACC_PUBLIC
    Code:
      stack=3, locals=4, args_size=3
         0: aload_0
         1: getfield      #2                  // Field lock:Ljava/util/concurrent/locks/ReentrantLock;
         4: invokevirtual #3                  // Method java/util/concurrent/locks/ReentrantLock.lock:()V
         7: aload_1
         8: getfield      #2                  // Field lock:Ljava/util/concurrent/locks/ReentrantLock;
        11: invokevirtual #3                  // Method java/util/concurrent/locks/ReentrantLock.lock:()V
        14: aload_0
        15: aload_1
        16: iload_2
        17: invokevirtual #5                  // Method doTransfer:(LacctManager4/Account;I)V
        20: aload_1
        21: getfield      #2                  // Field lock:Ljava/util/concurrent/locks/ReentrantLock;
        24: invokevirtual #4                  // Method java/util/concurrent/locks/ReentrantLock.unlock:()V
        27: aload_0
        28: getfield      #2                  // Field lock:Ljava/util/concurrent/locks/ReentrantLock;
        31: invokevirtual #4                  // Method java/util/concurrent/locks/ReentrantLock.unlock:()V
        34: return
      LineNumberTable:
        line 15: 0
        line 16: 7
        line 17: 14
        line 18: 20
        line 19: 27
        line 20: 34
      LocalVariableTable:
        Start  Length  Slot  Name   Signature
            0      35     0  this   LacctManager4/Account;
            0      35     1  target LacctManager4/Account;
            0      35     2  amount I;
            3      32     3  temp   I;
}
```


